{
  "app": {
    "about": {
      "butter": "Hi!!! I am Butterfree!!!",
      "title": "My Pokemon"
    },
    "main": {
      "table": {
        "action": {
          "tooltip": {
            "catch": "Catch a Pokemon",
            "wish": "Wishlist"
          }
        },
        "total": "{{total}} Pokemon"
      }
    },
    "models": {
      "catch-wish": {
        "catches": "Catches",
        "title": "Catch/Wish",
        "wishes": "Wishes"
      },
      "gender": {
        "type": {
          "female": "Female",
          "genderless": "Genderless",
          "male": "Male"
        }
      },
      "pokemon": {
        "columns": {
          "gender": "Gender",
          "id": "ID",
          "name": "Name"
        }
      }
    }
  }
}
